{"submission_stats": [{"date_time": "", "submission_id": "43958409", "problem_name": "A - King Escape", "submission_link": "http://codeforces.com/contest/1033/submission/43958409", "participant_id": "20233979", "contest_url": "http://codeforces.com/contest/1033/problem/A", "submission_lang": "GNU C++14", "time_consumed": "31\u00a0ms", "memory_consumed": "0\u00a0KB", "submission_verdict": "OK", "submission_verdict_text": "Accepted", "problem_id": ["1033", "A"]}], "submissionid": "43958409", "problem_name": "A - King Escape", "language": "GNU C++14", "verdict": "Accepted", "time_taken": ["31 ms"], "memory": "8 KB", "submitted_time": "2018-10-07 20:30:23", "judged_time": "2018-10-07 22:28:34", "program": ["#include <bits/stdc++.h>\r\nusing namespace std;\r\n\r\n#define                       pb push_back\r\n#define                       mp make_pair\r\n#define                           fs first\r\n#define                          sc second\r\n#define                           bg begin\r\n#define                       ll long long\r\n#define                     vi vector <ll>\r\n#define                       sll set <ll>\r\n#define             uos unordered_set <ll>\r\n#define        vii vector <pair <ll, ll> >\r\n#define                 mii map < ll, ll >\r\n#define        vii vector <pair <ll, ll> >\r\n#define  hello ios::sync_with_stdio(false);\r\n\r\nint main()\r\n{\r\n    hello\r\n    ll n; cin >> n;\r\n    ll ax, ay, bx, by, cx, cy;\r\n    cin >> bx >> by >> ax >> ay >> cx >> cy;\r\n\r\n    ll d1x = bx - ax;\r\n    ll d1y = by - ay;\r\n    ll d2x = bx - cx;\r\n    ll d2y = by - cy;\r\n\r\n    if (((d1x < 0 and d2x < 0) or (d1x > 0 and d2x > 0)) and ((d1y < 0 and d2y < 0) or (d1y > 0 and d2y > 0)))\r\n        cout << \"YES\";\r\n     else cout << \"NO\";\r\n    //  cout << endl << d1x << d2x << endl;\r\n    //  cout << d1y << d2y;\r\n    // if (ax < bx and cx < bx and ay < by and cy < by)\r\n    //     return cout << \"YES\", 0;\r\n    // else if ( ax > bx and ay > by and cx > ax and cy > by)\r\n    //     return cout << \"YES\", 0;\r\n    // else if (ax < bx and ay > by and cx < bx and cy > by)\r\n    //     return cout << \"YES\", 0;\r\n    // else if (ax > bx and cx > bx and ay < by and cy < by)\r\n    //     return cout << \"YES\", 0;\r\n    // else return cout << \"NO\", 0;\r\n}"], "testcases_data": [{"test_no": "1\r\n            ", "testcase_verdict": "Verdict: OK", "input_data": "8\r\n4 4\r\n1 3\r\n3 1\r\n", "output_data": "YES", "correct_answer": "YES\r\n", "comment": "ok answer is YES\r\n", "Time": ": 15 ms, ", "memory": ": 0 KB"}, {"test_no": "2\r\n            ", "testcase_verdict": "Verdict: OK", "input_data": "8\r\n4 4\r\n2 3\r\n1 6\r\n", "output_data": "NO", "correct_answer": "NO\r\n", "comment": "ok answer is NO\r\n", "Time": ": 15 ms, ", "memory": ": 0 KB"}, {"test_no": "3\r\n            ", "testcase_verdict": "Verdict: OK", "input_data": "8\r\n3 5\r\n1 2\r\n6 1\r\n", "output_data": "NO", "correct_answer": "NO\r\n", "comment": "ok answer is NO\r\n", "Time": ": 15 ms, ", "memory": ": 0 KB"}, {"test_no": "4\r\n            ", "testcase_verdict": "Verdict: OK", "input_data": "1000\r\n500 200\r\n350 300\r\n400 401\r\n", "output_data": "YES", "correct_answer": "YES\r\n", "comment": "ok answer is YES\r\n", "Time": ": 15 ms, ", "memory": ": 4 KB"}, {"test_no": "5\r\n            ", "testcase_verdict": "Verdict: OK", "input_data": "1000\r\n600 600\r\n700 653\r\n650 701\r\n", "output_data": "YES", "correct_answer": "YES\r\n", "comment": "ok answer is YES\r\n", "Time": ": 15 ms, ", "memory": ": 8 KB"}, {"test_no": "6\r\n            ", "testcase_verdict": "Verdict: OK", "input_data": "999\r\n999 999\r\n998 1\r\n1 998\r\n", "output_data": "YES", "correct_answer": "YES\r\n", "comment": "ok answer is YES\r\n", "Time": ": 0 ms, ", "memory": ": 0 KB"}, {"test_no": "7\r\n            ", "testcase_verdict": "Verdict: OK", "input_data": "3\r\n1 1\r\n3 2\r\n2 3\r\n", "output_data": "YES", "correct_answer": "YES\r\n", "comment": "ok answer is YES\r\n", "Time": ": 0 ms, ", "memory": ": 0 KB"}, {"test_no": "8\r\n            ", "testcase_verdict": "Verdict: OK", "input_data": "50\r\n2 3\r\n1 1\r\n50 50\r\n", "output_data": "NO", "correct_answer": "NO\r\n", "comment": "ok answer is NO\r\n", "Time": ": 31 ms, ", "memory": ": 4 KB"}, {"test_no": "9\r\n            ", "testcase_verdict": "Verdict: OK", "input_data": "75\r\n16 12\r\n75 75\r\n1 1\r\n", "output_data": "NO", "correct_answer": "NO\r\n", "comment": "ok answer is NO\r\n", "Time": ": 15 ms, ", "memory": ": 4 KB"}, {"test_no": "10\r\n            ", "testcase_verdict": "Verdict: OK", "input_data": "75\r\n16 12\r\n75 1\r\n1 75\r\n", "output_data": "NO", "correct_answer": "NO\r\n", "comment": "ok answer is NO\r\n", "Time": ": 15 ms, ", "memory": ": 0 KB"}, {"test_no": "11\r\n            ", "testcase_verdict": "Verdict: OK", "input_data": "4\r\n1 2\r\n4 1\r\n4 4\r\n", "output_data": "NO", "correct_answer": "NO\r\n", "comment": "ok answer is NO\r\n", "Time": ": 30 ms, ", "memory": ": 0 KB"}, {"test_no": "12\r\n            ", "testcase_verdict": "Verdict: OK", "input_data": "4\r\n1 2\r\n4 3\r\n4 4\r\n", "output_data": "YES", "correct_answer": "YES\r\n", "comment": "ok answer is YES\r\n", "Time": ": 15 ms, ", "memory": ": 4 KB"}, {"test_no": "13\r\n            ", "testcase_verdict": "Verdict: OK", "input_data": "4\r\n1 2\r\n3 1\r\n4 1\r\n", "output_data": "YES", "correct_answer": "YES\r\n", "comment": "ok answer is YES\r\n", "Time": ": 15 ms, ", "memory": ": 0 KB"}, {"test_no": "14\r\n            ", "testcase_verdict": "Verdict: OK", "input_data": "4\r\n2 3\r\n3 1\r\n4 2\r\n", "output_data": "YES", "correct_answer": "YES\r\n", "comment": "ok answer is YES\r\n", "Time": ": 0 ms, ", "memory": ": 0 KB"}, {"test_no": "15\r\n            ", "testcase_verdict": "Verdict: OK", "input_data": "20\r\n5 10\r\n7 7\r\n8 8\r\n", "output_data": "YES", "correct_answer": "YES\r\n", "comment": "ok answer is YES\r\n", "Time": ": 30 ms, ", "memory": ": 4 KB"}, {"test_no": "16\r\n            ", "testcase_verdict": "Verdict: OK", "input_data": "20\r\n9 10\r\n12 16\r\n13 17\r\n", "output_data": "YES", "correct_answer": "YES\r\n", "comment": "ok answer is YES\r\n", "Time": ": 15 ms, ", "memory": ": 4 KB"}, {"test_no": "17\r\n            ", "testcase_verdict": "Verdict: OK", "input_data": "20\r\n11 10\r\n18 12\r\n12 18\r\n", "output_data": "YES", "correct_answer": "YES\r\n", "comment": "ok answer is YES\r\n", "Time": ": 0 ms, ", "memory": ": 0 KB"}, {"test_no": "18\r\n            ", "testcase_verdict": "Verdict: OK", "input_data": "20\r\n11 10\r\n12 18\r\n18 11\r\n", "output_data": "YES", "correct_answer": "YES\r\n", "comment": "ok answer is YES\r\n", "Time": ": 15 ms, ", "memory": ": 4 KB"}, {"test_no": "19\r\n            ", "testcase_verdict": "Verdict: OK", "input_data": "1000\r\n500 500\r\n2 3\r\n700 3\r\n", "output_data": "NO", "correct_answer": "NO\r\n", "comment": "ok answer is NO\r\n", "Time": ": 15 ms, ", "memory": ": 0 KB"}, {"test_no": "20\r\n            ", "testcase_verdict": "Verdict: OK", "input_data": "1000\r\n500 500\r\n893 450\r\n891 449\r\n", "output_data": "YES", "correct_answer": "YES\r\n", "comment": "ok answer is YES\r\n", "Time": ": 15 ms, ", "memory": ": 4 KB"}, {"test_no": "21\r\n            ", "testcase_verdict": "Verdict: OK", "input_data": "1000\r\n400 500\r\n32 796\r\n415 888\r\n", "output_data": "NO", "correct_answer": "NO\r\n", "comment": "ok answer is NO\r\n", "Time": ": 15 ms, ", "memory": ": 0 KB"}, {"test_no": "22\r\n            ", "testcase_verdict": "Verdict: OK", "input_data": "1000\r\n350 112\r\n372 113\r\n352 113\r\n", "output_data": "YES", "correct_answer": "YES\r\n", "comment": "ok answer is YES\r\n", "Time": ": 0 ms, ", "memory": ": 0 KB"}, {"test_no": "23\r\n            ", "testcase_verdict": "Verdict: OK", "input_data": "3\r\n2 3\r\n1 1\r\n3 1\r\n", "output_data": "NO", "correct_answer": "NO\r\n", "comment": "ok answer is NO\r\n", "Time": ": 15 ms, ", "memory": ": 0 KB"}, {"test_no": "24\r\n            ", "testcase_verdict": "Verdict: OK", "input_data": "1000\r\n112 350\r\n113 372\r\n113 352\r\n", "output_data": "YES", "correct_answer": "YES\r\n", "comment": "ok answer is YES\r\n", "Time": ": 30 ms, ", "memory": ": 0 KB"}, {"test_no": "25\r\n            ", "testcase_verdict": "Verdict: OK", "input_data": "1000\r\n114 350\r\n113 372\r\n113 352\r\n", "output_data": "YES", "correct_answer": "YES\r\n", "comment": "ok answer is YES\r\n", "Time": ": 15 ms, ", "memory": ": 8 KB"}, {"test_no": "26\r\n            ", "testcase_verdict": "Verdict: OK", "input_data": "1000\r\n112 380\r\n113 372\r\n113 352\r\n", "output_data": "YES", "correct_answer": "YES\r\n", "comment": "ok answer is YES\r\n", "Time": ": 15 ms, ", "memory": ": 0 KB"}, {"test_no": "27\r\n            ", "testcase_verdict": "Verdict: OK", "input_data": "1000\r\n114 372\r\n112 350\r\n113 352\r\n", "output_data": "YES", "correct_answer": "YES\r\n", "comment": "ok answer is YES\r\n", "Time": ": 0 ms, ", "memory": ": 0 KB"}, {"test_no": "28\r\n            ", "testcase_verdict": "Verdict: OK", "input_data": "1000\r\n113 352\r\n114 372\r\n112 370\r\n", "output_data": "NO", "correct_answer": "NO\r\n", "comment": "ok answer is NO\r\n", "Time": ": 15 ms, ", "memory": ": 0 KB"}, {"test_no": "29\r\n            ", "testcase_verdict": "Verdict: OK", "input_data": "1000\r\n112 350\r\n113 352\r\n113 372\r\n", "output_data": "YES", "correct_answer": "YES\r\n", "comment": "ok answer is YES\r\n", "Time": ": 15 ms, ", "memory": ": 4 KB"}, {"test_no": "30\r\n            ", "testcase_verdict": "Verdict: OK", "input_data": "5\r\n5 4\r\n1 5\r\n1 3\r\n", "output_data": "NO", "correct_answer": "NO\r\n", "comment": "ok answer is NO\r\n", "Time": ": 15 ms, ", "memory": ": 4 KB"}, {"test_no": "31\r\n            ", "testcase_verdict": "Verdict: OK", "input_data": "5\r\n3 3\r\n4 1\r\n5 2\r\n", "output_data": "YES", "correct_answer": "YES\r\n", "comment": "ok answer is YES\r\n", "Time": ": 15 ms, ", "memory": ": 0 KB"}, {"test_no": "32\r\n            ", "testcase_verdict": "Verdict: OK", "input_data": "100\r\n2 6\r\n1 3\r\n3 4\r\n", "output_data": "NO", "correct_answer": "NO\r\n", "comment": "ok answer is NO\r\n", "Time": ": 15 ms, ", "memory": ": 4 KB"}, {"test_no": "33\r\n            ", "testcase_verdict": "Verdict: OK", "input_data": "5\r\n5 2\r\n3 3\r\n3 1\r\n", "output_data": "NO", "correct_answer": "NO\r\n", "comment": "ok answer is NO\r\n", "Time": ": 0 ms, ", "memory": ": 0 KB"}, {"test_no": "34\r\n            ", "testcase_verdict": "Verdict: OK", "input_data": "5\r\n2 4\r\n1 2\r\n3 2\r\n", "output_data": "NO", "correct_answer": "NO\r\n", "comment": "ok answer is NO\r\n", "Time": ": 15 ms, ", "memory": ": 8 KB"}, {"test_no": "35\r\n            ", "testcase_verdict": "Verdict: OK", "input_data": "10\r\n1 2\r\n2 4\r\n2 5\r\n", "output_data": "YES", "correct_answer": "YES\r\n", "comment": "ok answer is YES\r\n", "Time": ": 15 ms, ", "memory": ": 0 KB"}, {"test_no": "36\r\n            ", "testcase_verdict": "Verdict: OK", "input_data": "1000\r\n500 500\r\n498 504\r\n498 505\r\n", "output_data": "YES", "correct_answer": "YES\r\n", "comment": "ok answer is YES\r\n", "Time": ": 15 ms, ", "memory": ": 0 KB"}, {"test_no": "37\r\n            ", "testcase_verdict": "Verdict: OK", "input_data": "10\r\n1 1\r\n2 4\r\n4 2\r\n", "output_data": "YES", "correct_answer": "YES\r\n", "comment": "ok answer is YES\r\n", "Time": ": 15 ms, ", "memory": ": 4 KB"}, {"test_no": "38\r\n            ", "testcase_verdict": "Verdict: OK", "input_data": "100\r\n12 47\r\n24 26\r\n3 4\r\n", "output_data": "NO", "correct_answer": "NO\r\n", "comment": "ok answer is NO\r\n", "Time": ": 15 ms, ", "memory": ": 0 KB"}, {"test_no": "39\r\n            ", "testcase_verdict": "Verdict: OK", "input_data": "4\r\n3 1\r\n1 2\r\n1 4\r\n", "output_data": "YES", "correct_answer": "YES\r\n", "comment": "ok answer is YES\r\n", "Time": ": 15 ms, ", "memory": ": 0 KB"}, {"test_no": "40\r\n            ", "testcase_verdict": "Verdict: OK", "input_data": "6\r\n5 6\r\n3 5\r\n4 4\r\n", "output_data": "YES", "correct_answer": "YES\r\n", "comment": "ok answer is YES\r\n", "Time": ": 15 ms, ", "memory": ": 0 KB"}, {"test_no": "41\r\n            ", "testcase_verdict": "Verdict: OK", "input_data": "5\r\n1 2\r\n2 4\r\n2 5\r\n", "output_data": "YES", "correct_answer": "YES\r\n", "comment": "ok answer is YES\r\n", "Time": ": 15 ms, ", "memory": ": 0 KB"}, {"test_no": "42\r\n            ", "testcase_verdict": "Verdict: OK", "input_data": "1000\r\n500 2\r\n498 502\r\n498 499\r\n", "output_data": "YES", "correct_answer": "YES\r\n", "comment": "ok answer is YES\r\n", "Time": ": 31 ms, ", "memory": ": 4 KB"}], "username": "ltra_golu"}